pyultrasonic/__init__.py
pyultrasonic/__main__.py
pyultrasonic/output.py
pyultrasonic/sensor.py
pyultrasonic-0.1.2.dist-info/LICENSE
pyultrasonic-0.1.2.dist-info/METADATA
pyultrasonic-0.1.2.dist-info/WHEEL
pyultrasonic-0.1.2.dist-info/entry_points.txt
pyultrasonic-0.1.2.dist-info/top_level.txt
pyultrasonic-0.1.2.dist-info/RECORD
